asyncpg_lostream/__init__.py
asyncpg_lostream/__version__
asyncpg_lostream/lostream.py
asyncpg_lostream-0.1.2.dist-info/LICENSE
asyncpg_lostream-0.1.2.dist-info/METADATA
asyncpg_lostream-0.1.2.dist-info/WHEEL
asyncpg_lostream-0.1.2.dist-info/top_level.txt
asyncpg_lostream-0.1.2.dist-info/RECORD
