Metadata-Version: 2.1
Name: asyncpg-lostream
Version: 0.1.2
Summary: CRUD on PostgreSQL large objects using async drivers and asyncio. Data are read and written in chunks.
Home-page: https://github.com/Red-HAP/asyncpg-lostream
Author: Red Hat, Inc.
Author-email: info@ansible.com
Maintainer: HAP
Maintainer-email: hproctor@redhat.com
License: Apache-2.0
Project-URL: issues, https://github.com/Red-HAP/asyncpg-lostream/issues
Project-URL: wiki, https://github.com/Red-HAP/asyncpg-lostream/wiki
Keywords: asyncio,asyncpg,SQLAlchemy
Classifier: Development Status :: 4 - Beta
Classifier: Intended Audience :: Developers
Classifier: License :: OSI Approved :: Apache Software License
Classifier: Operating System :: OS Independent
Classifier: Programming Language :: Python :: 3.9
Classifier: Programming Language :: Python :: 3.10
Classifier: Programming Language :: Python :: 3.11
Classifier: Topic :: Database
Classifier: Topic :: Software Development :: Libraries :: Python Modules
Requires-Python: >=3.9
License-File: LICENSE
Requires-Dist: sqlalchemy[asyncio] (>=1.4)
Requires-Dist: asyncpg
